{
  "publicPath": "/_nuxt/",
  "all": [
    "../server/index.spa.html",
    "../server/index.ssr.html",
    "0080198.js",
    "0c2a605.js",
    "142c4ce.js",
    "17de215.js",
    "1fa8fb6.js",
    "25cf71c.js",
    "2baff7a.js",
    "3012980.js",
    "53f93e4.js",
    "6c62406.js",
    "7257640.js",
    "73d6ab2.js",
    "771bb0b.js",
    "80b7a84.js",
    "8856263.js",
    "88c9d70.js",
    "8f2ecf5.js",
    "8f8c3b4.js",
    "93863aa.js",
    "9fc64f4.js",
    "LICENSES",
    "a598cac.js",
    "af013f3.js",
    "b135c06.js",
    "b3c3b60.js",
    "c1049f6.js",
    "c92384d.js",
    "cbc4459.js",
    "cc3e738.js",
    "cffa0c2.js",
    "d4474d1.js",
    "de96902.js",
    "e201db2.js",
    "e4f1273.js",
    "ed94320.js",
    "ef2ff8f.js",
    "f82f729.js",
    "ffdfab2.js",
    "fonts/Avenir-LT-35-Light.e7bf75f.ttf",
    "fonts/BarlowCondensed-Regular.0bac2bb.ttf",
    "fonts/FontsFree-Net-Lulo-Clean-W01-One-Bold.cf6ce05.ttf",
    "fonts/Halimun-W7jn.d49fc08.ttf",
    "fonts/Kalam-Regular.ca4a04f.ttf"
  ],
  "initial": [
    "d4474d1.js",
    "2baff7a.js",
    "53f93e4.js",
    "cffa0c2.js"
  ],
  "async": [
    "0080198.js",
    "0c2a605.js",
    "142c4ce.js",
    "17de215.js",
    "1fa8fb6.js",
    "25cf71c.js",
    "3012980.js",
    "6c62406.js",
    "7257640.js",
    "73d6ab2.js",
    "771bb0b.js",
    "80b7a84.js",
    "8856263.js",
    "88c9d70.js",
    "8f2ecf5.js",
    "8f8c3b4.js",
    "93863aa.js",
    "9fc64f4.js",
    "a598cac.js",
    "af013f3.js",
    "b135c06.js",
    "b3c3b60.js",
    "c1049f6.js",
    "c92384d.js",
    "cbc4459.js",
    "cc3e738.js",
    "de96902.js",
    "e201db2.js",
    "e4f1273.js",
    "ed94320.js",
    "ef2ff8f.js",
    "f82f729.js",
    "ffdfab2.js"
  ],
  "modules": {
    "15755276": [
      31,
      42,
      40,
      43,
      44,
      41
    ],
    "16836170": [
      8
    ],
    "21866202": [
      10
    ],
    "25991135": [
      10
    ],
    "28737786": [
      10
    ],
    "41409468": [
      8
    ],
    "43271295": [
      9,
      14,
      23,
      6,
      18
    ],
    "49670236": [
      8
    ],
    "50973922": [
      15
    ],
    "54165536": [
      5
    ],
    "64984386": [
      10
    ],
    "68718707": [
      10
    ],
    "73776554": [
      10
    ],
    "76096751": [
      31,
      42,
      40,
      43,
      44,
      41
    ],
    "76403870": [
      8
    ],
    "78162064": [
      23
    ],
    "79023940": [
      10
    ],
    "81219854": [
      10
    ],
    "95072012": [
      8
    ],
    "35a250a4": [
      10
    ],
    "6d64f274": [
      8
    ],
    "556cdd8d": [
      10
    ],
    "3f19a4aa": [
      31,
      42,
      40,
      43,
      44,
      41
    ],
    "5b588668": [
      8
    ],
    "cf044a6e": [
      10
    ],
    "69968f9c": [
      10
    ],
    "7a0c8c09": [
      8
    ],
    "0f8f812a": [
      8
    ],
    "a0dba558": [
      8
    ],
    "2f94b12c": [
      8
    ],
    "7870eac1": [
      10
    ],
    "5c205532": [
      8
    ],
    "6c295334": [
      8
    ],
    "1b8a6c1a": [
      8
    ],
    "1f353445": [
      10
    ],
    "02e1df89": [
      10
    ],
    "7fa4060e": [
      10
    ],
    "0842c684": [
      10
    ],
    "a1cd7df0": [
      10
    ],
    "3cdb5394": [
      10
    ],
    "37444baf": [
      10
    ],
    "b36cf906": [
      8
    ],
    "336defed": [
      8
    ],
    "6409b3e8": [
      10
    ],
    "594adc19": [
      8
    ],
    "4ef7cade": [
      8
    ],
    "57362ea8": [
      8
    ],
    "46e6198c": [
      8
    ],
    "0599d657": [
      8
    ],
    "a2c2e790": [
      8
    ],
    "45ba9e6c": [
      10
    ],
    "183f72b0": [
      8
    ],
    "d48a576a": [
      10
    ],
    "45c57112": [
      8
    ],
    "5bf231e1": [
      8
    ],
    "5b0ee170": [
      10
    ],
    "e9aa6dfc": [
      8
    ],
    "570bb70e": [
      8
    ],
    "0b7272d0": [
      8
    ],
    "378c9a7b": [
      8
    ],
    "596510a1": [
      8
    ],
    "4853aa3a": [
      8
    ],
    "6c11b5ba": [
      8
    ],
    "0e071ab0": [
      8
    ],
    "6d285624": [
      8
    ],
    "3b2f7a3e": [
      8
    ],
    "ca306190": [
      8
    ],
    "7e448a15": [
      10
    ],
    "381970a5": [
      8
    ],
    "3fc4d785": [
      8
    ],
    "23d6bef4": [
      8
    ],
    "fd759c50": [
      8
    ],
    "0c6f741a": [
      8
    ],
    "809a26fa": [
      10
    ],
    "61f919c3": [
      10
    ],
    "4b108542": [
      8
    ],
    "f6bae5bc": [
      8
    ],
    "30dba1f5": [
      10
    ],
    "3e2238b2": [
      10
    ],
    "f725ed88": [
      10
    ],
    "c662b6f2": [
      10
    ],
    "194ec2c1": [
      8
    ],
    "422f433b": [
      8
    ],
    "8ff14d2c": [
      8
    ],
    "51954f91": [
      8
    ],
    "599e7080": [
      8
    ],
    "7f47bbe5": [
      8
    ],
    "62601e11": [
      10
    ],
    "52dd644d": [
      10
    ],
    "7a7cedfb": [
      10
    ],
    "a1d75564": [
      8
    ],
    "67e067ee": [
      8
    ],
    "22a02dc8": [
      8
    ],
    "4af65993": [
      8
    ],
    "437dbe4d": [
      10
    ],
    "079ef474": [
      8
    ],
    "38938d66": [
      8
    ],
    "66cdcd04": [
      8
    ],
    "1999f50c": [
      8
    ],
    "324b96be": [
      8
    ],
    "7e684f0a": [
      8
    ],
    "5acdae56": [
      10
    ],
    "473b1aad": [
      10
    ],
    "3bdd7525": [
      10
    ],
    "3de7d3ff": [
      10
    ],
    "7cb4c1bb": [
      8
    ],
    "1a3d8ce9": [
      31,
      42,
      40,
      43,
      44,
      41
    ],
    "67b20d8a": [
      31,
      42,
      40,
      43,
      44,
      41
    ],
    "fa99b4ba": [
      31,
      42,
      40,
      43,
      44,
      41
    ],
    "83f433ac": [
      31,
      42,
      40,
      43,
      44,
      41
    ],
    "130e2d52": [
      31,
      42,
      40,
      43,
      44,
      41
    ],
    "ae903b4c": [
      31,
      42,
      40,
      43,
      44,
      41
    ],
    "79e28e7a": [
      31,
      42,
      40,
      43,
      44,
      41
    ],
    "5834ffa2": [
      31,
      42,
      40,
      43,
      44,
      41
    ],
    "f71ca0dc": [
      31,
      42,
      40,
      43,
      44,
      41
    ],
    "7d14b918": [
      31,
      42,
      40,
      43,
      44,
      41
    ],
    "13e5e5cb": [
      31,
      42,
      40,
      43,
      44,
      41
    ],
    "0492d2f7": [
      31,
      42,
      40,
      43,
      44,
      41
    ],
    "594ee3e2": [
      31,
      42,
      40,
      43,
      44,
      41
    ],
    "1cd238a8": [
      31,
      42,
      40,
      43,
      44,
      41
    ],
    "2d680a02": [
      31,
      42,
      40,
      43,
      44,
      41
    ],
    "837a293a": [
      31,
      42,
      40,
      43,
      44,
      41
    ],
    "7a3fc7f4": [
      31,
      42,
      40,
      43,
      44,
      41
    ],
    "51e2ebb0": [
      31,
      42,
      40,
      43,
      44,
      41
    ],
    "72d366ab": [
      31,
      42,
      40,
      43,
      44,
      41
    ],
    "1b37a562": [
      31,
      42,
      40,
      43,
      44,
      41
    ],
    "15747c7a": [
      31,
      42,
      40,
      43,
      44,
      41
    ],
    "52935dd0": [
      31,
      42,
      40,
      43,
      44,
      41
    ],
    "98735d44": [
      31,
      42,
      40,
      43,
      44,
      41
    ],
    "063b764f": [
      31,
      42,
      40,
      43,
      44,
      41
    ],
    "333cb058": [
      31,
      42,
      40,
      43,
      44,
      41
    ],
    "4b79e3c4": [
      31,
      42,
      40,
      43,
      44,
      41
    ],
    "4ebf50eb": [
      31,
      42,
      40,
      43,
      44,
      41
    ],
    "0beaf2de": [
      31,
      42,
      40,
      43,
      44,
      41
    ],
    "e01db6ac": [
      31,
      42,
      40,
      43,
      44,
      41
    ],
    "af6b2d58": [
      31,
      42,
      40,
      43,
      44,
      41
    ],
    "9a92d18e": [
      31,
      42,
      40,
      43,
      44,
      41
    ],
    "60a49b3a": [
      8
    ],
    "75ff4d88": [
      8
    ],
    "5eefecb0": [
      8
    ],
    "37dfcfa4": [
      10
    ],
    "9b363e64": [
      10
    ],
    "b328e9f4": [
      10
    ],
    "29dd3c7a": [
      10
    ],
    "168dda82": [
      10
    ],
    "52c8d7a2": [
      8
    ],
    "2ac02bb0": [
      8
    ],
    "0b4631cd": [
      8
    ],
    "3796e567": [
      8
    ],
    "7534c0b3": [
      8
    ],
    "16ecee52": [
      10
    ],
    "5b638eb7": [
      10
    ],
    "62a78e46": [
      8
    ],
    "6075ec2e": [
      8
    ],
    "865e082e": [
      8
    ],
    "6aeb3154": [
      10
    ],
    "7fd63982": [
      10
    ],
    "19bf7d25": [
      10
    ],
    "cd9268ba": [
      10
    ],
    "0a96ca62": [
      10
    ],
    "788f62be": [
      8
    ],
    "009fcf50": [
      8
    ],
    "0e7b99d3": [
      8
    ],
    "262dfab2": [
      8
    ],
    "1af1c0db": [
      8
    ],
    "606744d4": [
      8
    ],
    "67b83654": [
      8
    ],
    "0eb50cb4": [
      8
    ],
    "3de825ac": [
      8
    ],
    "6425b969": [
      8
    ],
    "d5fa9166": [
      8
    ],
    "203cd61d": [
      8
    ],
    "15c0571a": [
      10
    ],
    "f3cf36fe": [
      10
    ],
    "49f8e356": [
      10
    ],
    "b6b94dca": [
      10
    ],
    "665046be": [
      31,
      42,
      40,
      43,
      44,
      41
    ],
    "6a39f1e2": [
      10
    ],
    "f1a93f92": [
      10
    ],
    "52cc5a0c": [
      10
    ],
    "653ce0cd": [
      10
    ],
    "3b8fa71e": [
      10
    ],
    "33fd4bf0": [
      10
    ],
    "ff9c2284": [
      10
    ],
    "5b433c32": [
      10
    ],
    "c53b6ada": [
      10
    ],
    "1cc857d0": [
      10
    ],
    "5c599ae5": [
      10
    ],
    "42581e10": [
      10
    ],
    "1221900c": [
      10
    ],
    "b934aef4": [
      10
    ],
    "c5a626a8": [
      10
    ],
    "77ee762b": [
      10
    ],
    "05520cbc": [
      10
    ],
    "3b1d0d4f": [
      10
    ],
    "1677ebd9": [
      10
    ],
    "8234bff4": [
      10
    ],
    "6ee4847e": [
      10
    ],
    "5efd5c78": [
      10
    ],
    "2e9136ef": [
      10
    ],
    "81e99b9c": [
      10
    ],
    "225cec68": [
      10
    ],
    "409c038a": [
      10
    ],
    "76bff752": [
      10
    ],
    "2c4a04ac": [
      10
    ],
    "7b652b2c": [
      8
    ],
    "7ae4ad9c": [
      10
    ],
    "0966b860": [
      8
    ],
    "6b529371": [
      8
    ],
    "5e20c421": [
      8
    ],
    "60cce076": [
      8
    ],
    "383337d2": [
      8
    ],
    "10dfb122": [
      8
    ],
    "0f01ba38": [
      8
    ],
    "b5e53f8c": [
      8
    ],
    "66c70284": [
      8
    ],
    "5344b629": [
      8
    ],
    "7fd7859b": [
      8
    ],
    "0b6b017d": [
      8
    ],
    "54b2cad6": [
      8
    ],
    "cfbdc0fc": [
      8
    ],
    "33d332f5": [
      8
    ],
    "2953eb0e": [
      8
    ],
    "1d49edd4": [
      8
    ],
    "20b8033d": [
      8
    ],
    "5b7287d4": [
      10
    ],
    "5c1d6824": [
      10
    ],
    "4db9b87b": [
      10
    ],
    "fd7bff0c": [
      10
    ],
    "0389a9f0": [
      10
    ],
    "6ac8c292": [
      10
    ],
    "621295ae": [
      10
    ],
    "4f0ddc23": [
      10
    ],
    "e3c8869a": [
      10
    ],
    "8a8799f4": [
      10
    ],
    "3c0ecb50": [
      10
    ],
    "fdfc36b8": [
      10
    ],
    "4fe91143": [
      10
    ],
    "0f5d501f": [
      10
    ],
    "5edee7c7": [
      10
    ],
    "728bf1a0": [
      31,
      42,
      40,
      43,
      44,
      41
    ],
    "6a6a2770": [
      10
    ],
    "2cb3f0b5": [
      8
    ],
    "2df3e424": [
      8
    ],
    "558069b0": [
      8
    ],
    "cab3c27a": [
      8
    ],
    "a6529bce": [
      8
    ],
    "17ebac63": [
      8
    ],
    "4e780238": [
      8
    ],
    "1a431b7a": [
      8
    ],
    "fc175000": [
      8
    ],
    "336a86f8": [
      8
    ],
    "b14fb944": [
      8
    ],
    "5a035ab2": [
      8
    ],
    "ebd43152": [
      8
    ],
    "dfedfacc": [
      8
    ],
    "2fbbd001": [
      8
    ],
    "579ca722": [
      8
    ],
    "5fa4eacd": [
      8
    ],
    "6f23b0a6": [
      8
    ],
    "575abfb8": [
      8
    ],
    "25f62f37": [
      8
    ],
    "488f0b39": [
      8
    ],
    "441576a6": [
      8
    ],
    "53417abb": [
      8
    ],
    "76687fd5": [
      8
    ],
    "ebd0e8da": [
      8
    ],
    "5fcc1670": [
      10
    ],
    "3b1b9cae": [
      10
    ],
    "7ddd2173": [
      10
    ],
    "7ba642ec": [
      10
    ],
    "f1af1922": [
      10
    ],
    "1a826993": [
      10
    ],
    "dd081c5e": [
      10
    ],
    "1155c818": [
      10
    ],
    "ae01f348": [
      8
    ],
    "56de8d22": [
      8
    ],
    "9a293fc2": [
      10
    ],
    "0a1d898b": [
      10
    ],
    "79a35ef3": [
      8
    ],
    "0815534b": [
      10
    ],
    "136694ce": [
      8
    ],
    "aa9450ea": [
      10
    ],
    "4e90e580": [
      10
    ],
    "42f1d045": [
      10
    ],
    "240594ba": [
      10
    ],
    "8960a132": [
      10
    ],
    "d1779a52": [
      10
    ],
    "20907e20": [
      8
    ],
    "6559168c": [
      8
    ],
    "6a9d7f8d": [
      31,
      42,
      40,
      43,
      44,
      41
    ],
    "70cf3888": [
      8
    ],
    "c9e9ee9e": [
      8
    ],
    "4cfa2a3a": [
      8
    ],
    "e55b435e": [
      8
    ],
    "40efd66c": [
      8
    ],
    "554a0da9": [
      8
    ],
    "2d0a2057": [
      8
    ],
    "660c13d7": [
      8
    ],
    "5c69f11d": [
      8
    ],
    "3ac4169d": [
      8
    ],
    "9f705ba2": [
      8
    ],
    "5e9cbc14": [
      8
    ],
    "e4cd07c8": [
      8
    ],
    "0f2a808e": [
      8
    ],
    "c03b4c4e": [
      8
    ],
    "c2c31708": [
      10
    ],
    "edf58476": [
      8
    ],
    "dc31d118": [
      8
    ],
    "4b9f5ba1": [
      8
    ],
    "14290cd2": [
      8
    ],
    "5972e074": [
      8
    ],
    "5047ff7d": [
      8
    ],
    "4b3bf96e": [
      8
    ],
    "195788be": [
      8
    ],
    "66e10723": [
      8
    ],
    "71a79b73": [
      8
    ],
    "26b3a285": [
      8
    ],
    "6ec4e051": [
      8
    ],
    "f1f2844e": [
      8
    ],
    "0d93c2e6": [
      8
    ],
    "201689a6": [
      8
    ],
    "2bf1bd95": [
      8
    ],
    "33cd5b6a": [
      8
    ],
    "44c9014a": [
      8
    ],
    "6d10a792": [
      8
    ],
    "5d6a16bd": [
      8
    ],
    "7e883d10": [
      8
    ],
    "1b832155": [
      8
    ],
    "1dfe767c": [
      8
    ],
    "7c960448": [
      8
    ],
    "08e0577d": [
      8
    ],
    "059a837b": [
      8
    ],
    "33f847c5": [
      8
    ],
    "8c7d027a": [
      8
    ],
    "1a2a1fb7": [
      8
    ],
    "58f4ba83": [
      8
    ],
    "28fbc434": [
      31,
      42,
      40,
      43,
      44,
      41
    ],
    "5718e674": [
      31,
      42,
      40,
      43,
      44,
      41
    ],
    "6a7e31b3": [
      31,
      42,
      40,
      43,
      44,
      41
    ],
    "453be158": [
      8
    ],
    "4617f9c8": [
      8
    ],
    "466453b2": [
      8
    ],
    "269fa970": [
      8
    ],
    "87fc90ee": [
      10
    ],
    "2c304928": [
      10
    ],
    "22e0526b": [
      10
    ],
    "cc162aaa": [
      10
    ],
    "0e19c954": [
      8
    ],
    "ce49fa1c": [
      8
    ],
    "471ca2de": [
      8
    ],
    "439a2e10": [
      8
    ],
    "50fb9420": [
      8
    ],
    "5db24d0a": [
      8
    ],
    "eca950e6": [
      8
    ],
    "bec920f0": [
      8
    ],
    "5fa632a3": [
      10
    ],
    "3ff8cc1f": [
      10
    ],
    "70af5623": [
      10
    ],
    "1103fd13": [
      10
    ],
    "b3c49b2c": [
      8
    ],
    "61ec3c41": [
      10
    ],
    "6c7bfd1d": [
      10
    ],
    "20dab252": [
      31,
      42,
      40,
      43,
      44,
      41
    ],
    "c4433d1a": [
      31,
      42,
      40,
      43,
      44,
      41
    ],
    "3f86ee95": [
      31,
      42,
      40,
      43,
      44,
      41
    ],
    "6bfa7a3f": [
      31,
      42,
      40,
      43,
      44,
      41
    ],
    "67a5c0dd": [
      31,
      42,
      40,
      43,
      44,
      41
    ],
    "141b4882": [
      31,
      42,
      40,
      43,
      44,
      41
    ],
    "b0526c90": [
      31,
      42,
      40,
      43,
      44,
      41
    ],
    "0f2ee06c": [
      8
    ],
    "662c62dc": [
      8
    ],
    "be3183ee": [
      31,
      42,
      40,
      43,
      44,
      41
    ],
    "a8ba4e0c": [
      10
    ],
    "27af6c70": [
      31,
      42,
      40,
      43,
      44,
      41
    ],
    "0a752f55": [
      8
    ],
    "0c5f1fbf": [
      8
    ],
    "56b7cf40": [
      8
    ],
    "737abcba": [
      8
    ],
    "30908bea": [
      8
    ],
    "2ea3a4dc": [
      8
    ],
    "084c676e": [
      8
    ],
    "4cd6a5cd": [
      8
    ],
    "1aa207fd": [
      8
    ],
    "7c5732f1": [
      8
    ],
    "6c8eb842": [
      8
    ],
    "49bbd0cf": [
      8
    ],
    "7c4db646": [
      8
    ],
    "5ce189a7": [
      8
    ],
    "51d86183": [
      8
    ],
    "0f23be10": [
      31,
      42,
      40,
      43,
      44,
      41
    ],
    "74b2bfc8": [
      8
    ],
    "41da72ec": [
      8
    ],
    "64e2d1ea": [
      8
    ],
    "35680f2e": [
      8
    ],
    "27199cae": [
      8
    ],
    "7092caee": [
      31,
      42,
      40,
      43,
      44,
      41
    ],
    "6211d1ca": [
      31,
      42,
      40,
      43,
      44,
      41
    ],
    "114a19b0": [
      10
    ],
    "af36c69c": [
      10
    ],
    "5957472e": [
      31,
      42,
      40,
      43,
      44,
      41
    ],
    "1ce5df4a": [
      31,
      42,
      40,
      43,
      44,
      41
    ],
    "900e63ce": [
      31,
      42,
      40,
      43,
      44,
      41
    ],
    "1697735c": [
      31,
      42,
      40,
      43,
      44,
      41
    ],
    "10b77c5a": [
      10
    ],
    "e92ec2fc": [
      31,
      42,
      40,
      43,
      44,
      41
    ],
    "149f221c": [
      31,
      42,
      40,
      43,
      44,
      41
    ],
    "2422b600": [
      31,
      42,
      40,
      43,
      44,
      41
    ],
    "a5fb6158": [
      31,
      42,
      40,
      43,
      44,
      41
    ],
    "de373fe6": [
      31,
      42,
      40,
      43,
      44,
      41
    ],
    "54d28f44": [
      10
    ],
    "20f20026": [
      31,
      42,
      40,
      43,
      44,
      41
    ],
    "42e2abda": [
      31,
      42,
      40,
      43,
      44,
      41
    ],
    "6d9cf262": [
      10
    ],
    "15c06728": [
      10
    ],
    "503586f4": [
      8
    ],
    "37ff4f60": [
      8
    ],
    "77473a86": [
      8
    ],
    "c4d4a414": [
      8
    ],
    "751c34a9": [
      8
    ],
    "09d13045": [
      8
    ],
    "c29d7ef2": [
      10
    ],
    "a98a5886": [
      10
    ],
    "58644f9b": [
      8
    ],
    "1b078ba6": [
      8
    ],
    "5a18c2e0": [
      8
    ],
    "0a7730be": [
      8
    ],
    "09ccd6e4": [
      8
    ],
    "3142d1c7": [
      8
    ],
    "655f63d2": [
      10
    ],
    "e6bca73c": [
      10
    ],
    "21e71b6c": [
      10
    ],
    "ad61f430": [
      10
    ],
    "5a58af72": [
      10
    ],
    "4740c928": [
      10
    ],
    "59d66914": [
      10
    ],
    "816a4232": [
      8
    ],
    "50f20bd0": [
      10
    ],
    "6ccc6922": [
      10
    ],
    "f9dd1db0": [
      10
    ],
    "4691749c": [
      10
    ],
    "39aa54c5": [
      10
    ],
    "7da5a262": [
      10
    ],
    "0e672b14": [
      8
    ],
    "42d9d688": [
      10
    ],
    "1dee933e": [
      10
    ],
    "0d5d8d21": [
      10
    ],
    "7635f457": [
      10
    ],
    "4478d694": [
      10
    ],
    "2fbeb2ca": [
      10
    ],
    "de388e70": [
      10
    ],
    "0e596352": [
      10
    ],
    "29f768f0": [
      10
    ],
    "9d0b7a0c": [
      10
    ],
    "4d58a330": [
      10
    ],
    "e8efa41c": [
      10
    ],
    "12eb9248": [
      10
    ],
    "7815885c": [
      10
    ],
    "001d827c": [
      10
    ],
    "71a8f386": [
      10
    ],
    "f6fb83ee": [
      10
    ],
    "0c77de5e": [
      10
    ],
    "d80a8f30": [
      10
    ],
    "45a8cc3c": [
      10
    ],
    "727108ec": [
      10
    ],
    "670864ec": [
      10
    ],
    "3e073e94": [
      10
    ],
    "136c52c8": [
      10
    ],
    "74be5b5c": [
      10
    ],
    "11f9a2d4": [
      10
    ],
    "e76ec4c0": [
      10
    ],
    "d3794b8e": [
      31,
      42,
      40,
      43,
      44,
      41
    ],
    "671dbb82": [
      31,
      42,
      40,
      43,
      44,
      41
    ],
    "8688c8d0": [
      31,
      42,
      40,
      43,
      44,
      41
    ],
    "4261283e": [
      31,
      42,
      40,
      43,
      44,
      41
    ],
    "7fba6143": [
      31,
      42,
      40,
      43,
      44,
      41
    ],
    "a0180fe4": [
      8
    ],
    "20064f51": [
      8
    ],
    "7cbd98c2": [
      8
    ],
    "f9a832dc": [
      8
    ],
    "50b71671": [
      8
    ],
    "acc3a014": [
      8
    ],
    "6e8d355c": [
      8
    ],
    "30994c4d": [
      8
    ],
    "371324cc": [
      8
    ],
    "12086f76": [
      8
    ],
    "287bb9e6": [
      8
    ],
    "c6183bd0": [
      8
    ],
    "e435d300": [
      8
    ],
    "32e3832a": [
      8
    ],
    "464c128d": [
      8
    ],
    "1065fb60": [
      8
    ],
    "8345e992": [
      8
    ],
    "49f18eeb": [
      8
    ],
    "ff486050": [
      31,
      42,
      40,
      43,
      44,
      41
    ],
    "44f4b987": [
      31,
      42,
      40,
      43,
      44,
      41
    ],
    "2e1307c0": [
      31,
      42,
      40,
      43,
      44,
      41
    ],
    "26142ff2": [
      31,
      42,
      40,
      43,
      44,
      41
    ],
    "6410a205": [
      31,
      42,
      40,
      43,
      44,
      41
    ],
    "0c6a0654": [
      6
    ],
    "f18f451e": [
      10
    ],
    "02da1848": [
      10
    ],
    "a2e162fa": [
      10
    ],
    "2e4799f6": [
      10
    ],
    "0279e46b": [
      10
    ],
    "f9288cf2": [
      10
    ],
    "370259e4": [
      10
    ],
    "29b8018e": [
      10
    ],
    "6a49a886": [
      10
    ],
    "1935e965": [
      10
    ],
    "1d792606": [
      10
    ],
    "ee4d7e3a": [
      10
    ],
    "1dc9064b": [
      10
    ],
    "253a828c": [
      10
    ],
    "14dc882e": [
      10
    ],
    "db684d3a": [
      23
    ],
    "93c01252": [
      23
    ],
    "5fe30a57": [
      6
    ],
    "902d0c4e": [
      7,
      36
    ],
    "172ed930": [
      14
    ],
    "2b8ce7b8": [
      14
    ],
    "eb5a40e2": [
      27
    ],
    "9ad40c02": [
      23
    ],
    "14915fe9": [
      15
    ],
    "46e24ddc": [
      21,
      29
    ],
    "76c76b6b": [
      13,
      29
    ],
    "fb47a846": [
      33,
      14
    ],
    "d5a8d0d6": [
      4,
      14,
      6,
      18
    ],
    "252d320d": [
      19,
      14,
      23,
      6
    ],
    "b4cc1bce": [
      35
    ],
    "2d02ebec": [
      2
    ],
    "45b5fb92": [
      6
    ],
    "13569cb9": [
      6
    ],
    "2e12b65b": [
      6
    ],
    "ce9c5d3a": [
      6
    ],
    "03b28f76": [
      6
    ],
    "1ae208c2": [
      6
    ],
    "34eb1003": [
      6
    ],
    "178d027a": [
      6
    ],
    "5548dec3": [
      14
    ],
    "7f10dbf3": [
      14
    ],
    "5f1e1734": [
      14
    ],
    "0e6276ba": [
      14
    ],
    "5c809536": [
      14
    ],
    "f560f23a": [
      14
    ],
    "a484c7f2": [
      14
    ],
    "31cee3d2": [
      14
    ],
    "0338050a": [
      14
    ],
    "5c5dd223": [
      14
    ],
    "247a0207": [
      6
    ],
    "d9c051d2": [
      6
    ],
    "5926e713": [
      7,
      36
    ],
    "469a5a80": [
      7,
      36
    ],
    "23460f94": [
      36
    ],
    "1a58d49e": [
      36
    ],
    "67ba1e18": [
      36
    ],
    "53a5cafe": [
      36
    ],
    "2350c234": [
      14
    ],
    "71de3df2": [
      14
    ],
    "53f0f388": [
      14
    ],
    "a4d26fdc": [
      14
    ],
    "becd2270": [
      14
    ],
    "0b81795c": [
      14
    ],
    "1f3e8dbc": [
      14
    ],
    "165152c6": [
      14
    ],
    "116a2148": [
      14
    ],
    "78c2be5c": [
      14
    ],
    "c4f16640": [
      30,
      14
    ],
    "d6cbdc2c": [
      30,
      14
    ],
    "5c2c336e": [
      27
    ],
    "304e3276": [
      27
    ],
    "cc75640c": [
      23
    ],
    "2fb90bc2": [
      23
    ],
    "bc00de4e": [
      23
    ],
    "219fc0cd": [
      23
    ],
    "739949b4": [
      23
    ],
    "0daf3973": [
      23
    ],
    "6225fad0": [
      23
    ],
    "2ac33e78": [
      23
    ],
    "18184d1a": [
      23
    ],
    "1b1b35e9": [
      23
    ],
    "f3283894": [
      23
    ],
    "ba99e2f0": [
      23
    ],
    "8c60cd22": [
      23
    ],
    "f46ea5dc": [
      23
    ],
    "3b54e346": [
      23
    ],
    "18159cf6": [
      23
    ],
    "49c9cf5e": [
      23
    ],
    "0efe05eb": [
      23
    ],
    "8e83aa2e": [
      23
    ],
    "61faef26": [
      23
    ],
    "be41ba62": [
      23
    ],
    "6d80203e": [
      23
    ],
    "02db4cbc": [
      23
    ],
    "0b3baaa2": [
      23
    ],
    "637e4e62": [
      15
    ],
    "2fc089d4": [
      21,
      29
    ],
    "54d9a2fa": [
      21,
      29
    ],
    "9720f558": [
      29
    ],
    "74bde944": [
      29
    ],
    "76df3271": [
      13,
      29
    ],
    "1ec849b8": [
      13,
      29
    ],
    "f58574d2": [
      33,
      14
    ],
    "4315b344": [
      33,
      14
    ],
    "531bd7cf": [
      4,
      14,
      6,
      18
    ],
    "acc46688": [
      4,
      14,
      6,
      18
    ],
    "77ed37c8": [
      18
    ],
    "153a3b5c": [
      18
    ],
    "04616d57": [
      18
    ],
    "228ac2e1": [
      18
    ],
    "ea2ebbf6": [
      6
    ],
    "fb77cc48": [
      6
    ],
    "09c6f3e6": [
      6
    ],
    "b4ceec08": [
      6
    ],
    "787c40f4": [
      6
    ],
    "90bdd6b0": [
      6
    ],
    "69d59432": [
      6
    ],
    "cc9d9930": [
      6
    ],
    "1726ddf2": [
      6
    ],
    "b21a5288": [
      6
    ],
    "3c3845c6": [
      6
    ],
    "6a79cc3b": [
      18
    ],
    "b8b83176": [
      18
    ],
    "5997f860": [
      18
    ],
    "6c2d984c": [
      18
    ],
    "280e4bc7": [
      19,
      14,
      23,
      6
    ],
    "34328d18": [
      19,
      14,
      23,
      6
    ],
    "011752cf": [
      9,
      14,
      23,
      6,
      18
    ],
    "579947bc": [
      9,
      14,
      23,
      6,
      18
    ],
    "244e9778": [
      9,
      14,
      23,
      6,
      18
    ],
    "755b8e4e": [
      9,
      14,
      23,
      6,
      18
    ],
    "46d75f53": [
      35
    ],
    "344ad2c0": [
      35
    ],
    "2a1a8872": [
      2
    ],
    "0261f036": [
      2
    ],
    "3d7b6baf": [
      29
    ],
    "b3ea8dd0": [
      16
    ],
    "186b1b23": [
      18
    ],
    "5faaa056": [
      18
    ],
    "1fba192b": [
      18
    ],
    "95ae4f74": [
      18
    ],
    "543d5114": [
      18
    ],
    "303cc13c": [
      18
    ],
    "3921a4be": [
      18
    ],
    "6113b064": [
      18
    ],
    "8fb2de7a": [
      18
    ],
    "4234abec": [
      18
    ],
    "6de770f6": [
      18
    ],
    "ea54354a": [
      18
    ],
    "32b30872": [
      18
    ],
    "6f28bb3f": [
      18
    ],
    "182bc75e": [
      30,
      14
    ],
    "6951fc75": [
      30,
      14
    ],
    "41796a3a": [
      30,
      14
    ],
    "15c18af5": [
      30,
      14
    ],
    "230cf182": [
      30,
      14
    ],
    "4a0ec63b": [
      30,
      14
    ],
    "c54aaf84": [
      9,
      14,
      23,
      6,
      18
    ],
    "63f4dd8e": [
      9,
      14,
      23,
      6,
      18
    ],
    "a60d5458": [
      9,
      14,
      23,
      6,
      18
    ],
    "8e781a8e": [
      9,
      14,
      23,
      6,
      18
    ],
    "36af042f": [
      9,
      14,
      23,
      6,
      18
    ],
    "7a6d169f": [
      9,
      14,
      23,
      6,
      18
    ],
    "6c5f3aa2": [
      35
    ],
    "7b3e06b3": [
      35
    ],
    "6b9f1b03": [
      35
    ],
    "c92daf9a": [
      35
    ],
    "3a082ede": [
      35
    ],
    "4fb64d82": [
      35
    ],
    "abcef02c": [
      7,
      36
    ],
    "42d1279d": [
      7,
      36
    ],
    "7b1e83b0": [
      7,
      36
    ],
    "62fc491d": [
      7,
      36
    ],
    "de4c5bfa": [
      7,
      36
    ],
    "098092a8": [
      34
    ],
    "6f92d470": [
      34
    ],
    "a26b64b4": [
      34
    ],
    "fa301170": [
      34
    ],
    "7d336181": [
      34
    ],
    "22a16455": [
      17
    ],
    "66dca906": [
      17
    ],
    "71e52b63": [
      17
    ],
    "51bc59fd": [
      17
    ],
    "17269fb0": [
      17
    ],
    "bf1c6e1e": [
      12
    ],
    "42ae8926": [
      12
    ],
    "11c956fe": [
      12
    ],
    "ca59aab4": [
      12
    ],
    "fe5dfa48": [
      12
    ],
    "b6de3c2a": [
      27
    ],
    "6fd5f3f6": [
      27
    ],
    "3edf4807": [
      27
    ],
    "ec0470f6": [
      27
    ],
    "1752d122": [
      27
    ],
    "d90ff474": [
      39,
      14,
      23
    ],
    "1ab62b5c": [
      39,
      14,
      23
    ],
    "f3696068": [
      39,
      14,
      23
    ],
    "12d00bd2": [
      39,
      14,
      23
    ],
    "54b463a7": [
      39,
      14,
      23
    ],
    "2899bb7d": [
      24
    ],
    "5065b1b4": [
      24
    ],
    "0120487b": [
      24
    ],
    "359ec034": [
      24
    ],
    "004ca000": [
      24
    ],
    "c59881f4": [
      15
    ],
    "d309d87e": [
      15
    ],
    "4e0e89d2": [
      15
    ],
    "1ba5c241": [
      15
    ],
    "5ed3e2d2": [
      15
    ],
    "72604d30": [
      21,
      29
    ],
    "76ba3dee": [
      21,
      29
    ],
    "732558bc": [
      21,
      29
    ],
    "d2354124": [
      21,
      29
    ],
    "d6533106": [
      21,
      29
    ],
    "a4baeef8": [
      13,
      29
    ],
    "2dd533c3": [
      13,
      29
    ],
    "8a9fc058": [
      13,
      29
    ],
    "ca39fb7a": [
      13,
      29
    ],
    "67b03cd9": [
      13,
      29
    ],
    "4b0e1554": [
      25,
      14,
      23
    ],
    "46b2b818": [
      25,
      14,
      23
    ],
    "5edf27fc": [
      25,
      14,
      23
    ],
    "229832d0": [
      25,
      14,
      23
    ],
    "068e0647": [
      25,
      14,
      23
    ],
    "1f1ff47f": [
      20
    ],
    "901cd13c": [
      20
    ],
    "b4b4d78e": [
      20
    ],
    "24ff65e2": [
      20
    ],
    "52a5b13e": [
      20
    ],
    "05b58145": [
      3,
      14
    ],
    "cc4ac3d6": [
      3,
      14
    ],
    "23b3071a": [
      3,
      14
    ],
    "1f054c95": [
      3,
      14
    ],
    "70ae0138": [
      3,
      14
    ],
    "310016b2": [
      26
    ],
    "58f47df4": [
      26
    ],
    "452551e0": [
      26
    ],
    "43b2df74": [
      26
    ],
    "6249ff8a": [
      26
    ],
    "0f3a3ce5": [
      38
    ],
    "f9d3fecc": [
      38
    ],
    "52f6098d": [
      38
    ],
    "3dc7621a": [
      38
    ],
    "215f1d68": [
      38
    ],
    "77ba26ba": [
      33,
      14
    ],
    "0caf86f2": [
      33,
      14
    ],
    "6ac14dcf": [
      33,
      14
    ],
    "2e543e07": [
      33,
      14
    ],
    "5dc4d16a": [
      33,
      14
    ],
    "dfe3fce8": [
      4,
      14,
      6,
      18
    ],
    "39d448dd": [
      4,
      14,
      6,
      18
    ],
    "37c37046": [
      4,
      14,
      6,
      18
    ],
    "2492aa5d": [
      4,
      14,
      6,
      18
    ],
    "7d0dc2be": [
      4,
      14,
      6,
      18
    ],
    "9e3ea256": [
      19,
      14,
      23,
      6
    ],
    "72b63cb3": [
      19,
      14,
      23,
      6
    ],
    "6a1407dd": [
      19,
      14,
      23,
      6
    ],
    "b13b839a": [
      19,
      14,
      23,
      6
    ],
    "5d178b78": [
      19,
      14,
      23,
      6
    ],
    "4c6e163f": [
      5
    ],
    "753f2e0e": [
      5
    ],
    "ea0db836": [
      5
    ],
    "e95f0904": [
      5
    ],
    "4efa5a0e": [
      2
    ],
    "9d345978": [
      2
    ],
    "369081c4": [
      2
    ],
    "0372b422": [
      36
    ],
    "167ebf4f": [
      36
    ],
    "f1ca9d5e": [
      36
    ],
    "3259c9dc": [
      36
    ],
    "57b39988": [
      36
    ]
  },
  "assetsMapping": {
    "48c4692d": [
      "0080198.js"
    ],
    "b6ff1f1a": [
      "0c2a605.js"
    ],
    "190a9fc1": [
      "142c4ce.js"
    ],
    "65e008c6": [
      "17de215.js"
    ],
    "721727e8": [
      "1fa8fb6.js"
    ],
    "2aff1868": [
      "25cf71c.js"
    ],
    "085a35c4": [
      "2baff7a.js"
    ],
    "61eb211a": [
      "3012980.js"
    ],
    "7ea24c87": [
      "53f93e4.js"
    ],
    "0279415a": [
      "6c62406.js"
    ],
    "1bd60353": [
      "7257640.js"
    ],
    "f5e23a9c": [
      "73d6ab2.js"
    ],
    "335642d6": [
      "771bb0b.js"
    ],
    "b7049298": [
      "80b7a84.js"
    ],
    "bba68bf6": [
      "8856263.js"
    ],
    "b70f48fa": [
      "88c9d70.js"
    ],
    "fa597012": [
      "8f2ecf5.js"
    ],
    "163eda4a": [
      "8f8c3b4.js"
    ],
    "ea00f7a6": [
      "93863aa.js"
    ],
    "294c67dc": [
      "9fc64f4.js"
    ],
    "40fd228e": [
      "a598cac.js"
    ],
    "7906cd2b": [
      "af013f3.js"
    ],
    "9f08fbf8": [
      "b135c06.js"
    ],
    "81294cd8": [
      "b3c3b60.js"
    ],
    "073c7fcd": [
      "c1049f6.js"
    ],
    "4f69c3d1": [
      "c92384d.js"
    ],
    "69fafc58": [
      "cbc4459.js"
    ],
    "1124c2e8": [
      "cc3e738.js"
    ],
    "1a3ae26b": [
      "cffa0c2.js"
    ],
    "6fca0322": [
      "d4474d1.js"
    ],
    "3e17a1d0": [
      "de96902.js"
    ],
    "2afd58e4": [
      "e201db2.js"
    ],
    "2a130dde": [
      "e4f1273.js"
    ],
    "f54bfc30": [
      "ed94320.js"
    ],
    "43a7fec0": [
      "ef2ff8f.js"
    ],
    "28bc4372": [
      "f82f729.js"
    ],
    "29bd80b0": [
      "ffdfab2.js"
    ]
  }
}